autonormalize/__init__.py
autonormalize/autonormalize.py
autonormalize/classes.py
autonormalize/dfd.py
autonormalize/normalize.py
autonormalize/examples/example_3
autonormalize/tests/__init__.py
autonormalize/tests/test_classes.py
autonormalize/tests/test_dfd.py
autonormalize/tests/test_example.py
autonormalize/tests/test_normalize.py
autonormalize/tests/test_version.py
autonormalize-2.0.1.dist-info/LICENSE
autonormalize-2.0.1.dist-info/METADATA
autonormalize-2.0.1.dist-info/WHEEL
autonormalize-2.0.1.dist-info/entry_points.txt
autonormalize-2.0.1.dist-info/top_level.txt
autonormalize-2.0.1.dist-info/RECORD
