Metadata-Version: 2.1
Name: autonormalize
Version: 2.0.1
Summary: a library for automated table normalization
Home-page: https://github.com/alteryx/autonormalize
Author: Alteryx, Inc.
Author-email: support@featurelabs.com
License: BSD 3-clause
Platform: UNKNOWN
Classifier: Development Status :: 3 - Alpha
Classifier: Intended Audience :: Developers
Classifier: Programming Language :: Python :: 3
Classifier: Programming Language :: Python :: 3.7
Classifier: Programming Language :: Python :: 3.8
Classifier: Programming Language :: Python :: 3.9
Requires-Python: >=3.7, <4
License-File: LICENSE
Requires-Dist: featuretools (>=1.0.0)
Requires-Dist: numpy (>=1.13.3)
Requires-Dist: pandas (>=0.23.0)
Requires-Dist: tqdm (>=4.19.2)
Requires-Dist: graphviz (>=0.8.4)
